collibra_catalog_classification/__init__.py
collibra_catalog_classification/api_client.py
collibra_catalog_classification/configuration.py
collibra_catalog_classification/rest.py
collibra_catalog_classification/api/__init__.py
collibra_catalog_classification/api/classification_data_category_api.py
collibra_catalog_classification/api/classification_process_api.py
collibra_catalog_classification/models/__init__.py
collibra_catalog_classification/models/classification.py
collibra_catalog_classification/models/classification_process_request.py
collibra_catalog_classification/models/classification_process_response.py
collibra_catalog_classification/models/data_class_data_category_connection.py
collibra_catalog_classification/models/data_class_data_category_connections_paged_response.py
collibra_catalog_classification/models/named_resource_reference_impl.py
collibra_catalog_classification/models/resource_type.py
collibra_catalog_classification/models/standard_error_response.py
test/__init__.py
test/test_classification.py
test/test_classification_data_category_api.py
test/test_classification_process_api.py
test/test_classification_process_request.py
test/test_classification_process_response.py
test/test_data_class_data_category_connection.py
test/test_data_class_data_category_connections_paged_response.py
test/test_named_resource_reference_impl.py
test/test_resource_type.py
test/test_standard_error_response.py
collibra_catalog_classification_200-2.0.0.dist-info/METADATA
collibra_catalog_classification_200-2.0.0.dist-info/WHEEL
collibra_catalog_classification_200-2.0.0.dist-info/top_level.txt
collibra_catalog_classification_200-2.0.0.dist-info/RECORD
